dooray_api_wrapper/__init__.py
dooray_api_wrapper/common/__init__.py
dooray_api_wrapper/common/dooray_request.py
dooray_api_wrapper/const/__init__.py
dooray_api_wrapper/const/const.py
dooray_api_wrapper/dooray/__init__.py
dooray_api_wrapper/dooray/project.py
dooray_api_wrapper/dooray/wiki.py
dooray_api_wrapper/structure/__init__.py
dooray_api_wrapper/structure/response_header.py
dooray_api_wrapper/structure/response_result.py
dooray_api_wrapper/structure/schema.py
dooray_api_wrapper/tool/wiki.py
dooray_api_wrapper-0.0.5.dist-info/LICENSE
dooray_api_wrapper-0.0.5.dist-info/METADATA
dooray_api_wrapper-0.0.5.dist-info/WHEEL
dooray_api_wrapper-0.0.5.dist-info/top_level.txt
dooray_api_wrapper-0.0.5.dist-info/RECORD
