Metadata-Version: 2.1
Name: dooray_api_wrapper
Version: 0.0.5
Summary: Wrapper of NHN Dooray API
Author-email: jooss287 <jooss287@gmail.com>
Project-URL: Homepage, https://github.com/Jooss287/dooray-api-wrapper
Project-URL: Issues, https://github.com/Jooss287/dooray-api-wrapper/issues
Classifier: Programming Language :: Python :: 3
Classifier: License :: OSI Approved :: MIT License
Classifier: Operating System :: OS Independent
Requires-Python: >=3.8
License-File: LICENSE
Requires-Dist: requests
Requires-Dist: requests-cache
Requires-Dist: pydantic
Requires-Dist: python-dotenv
